<?xml version='1.0' encoding="UTF-8"?>

<window>

	<main x=0 y=0 width=1024 height=768 />

	<static_icon x="128" y="0" width="854" height="107">
		<texture x="128" y="0" width="768" height="107">ui\ui_character_16</texture>
	</static_icon>
	<static_icon x="514" y="0" width="382" height="99" stretch="1">
		<!--texture x="684" y="0" width="340" height="99">ui\ui_actor_trade_menu</texture-->
	</static_icon>

	<our_bag_static x="128" y="98" width="382" height="671" stretch="1">
		<texture>ui_actor_menu_carbody</texture>
		<text x="297" y="14" font="graffiti22" a="255" r="238" g="153" b="26" complex_mode="1"/>
	</our_bag_static>

	<dragdrop_list_our x="11" y="54" width="358" height="560"
			cell_width = "26" cell_height="35" rows_num="16" cols_num="13" 
			group_similar="1" unlimited="1"/>

	<others_bag_static x="514" y="98" width="382" height="671" stretch="1">
		<texture>ui_actor_menu_carbody</texture>
		<text x="12" y="12" font="graffiti22" r="255" g="255" b="255" a="128">st_items</text>
	</others_bag_static>

	<dragdrop_list_other x="11" y="54" width="358" height="560"
			cell_width = "26" cell_height="35" rows_num="16" cols_num="13" 
			group_similar="1" unlimited="1"/>

	<frame_window x="1030" y="181" width="340" height="588">
		<texture>ui_frame_0</texture>		
		<!--_left_top_texture x="5" y="10">ui\ui_inv_info_over_lt</_left_top_texture-->
	</frame_window>

	<descr_static x="0" y="0" width="340" height="588">
		<texture>ui_actor_menu_descr_c</texture>
	</descr_static>

	<top_background x="0" y="0" width="128" height="768">
		<texture x="0" y="0" width="128" height="768">ui\ui_actor_menu_back</texture>
	</top_background>

	<bottom_background x="896" y="0" width="128" height="768">
		<texture x="896" y="0" width="128" height="768">ui\ui_actor_menu_back</texture>
	</bottom_background>

	<take_all_btn x="522" y="734" width="363" height="25" hR="255" hB="83" hG="179" highlight_text="1" accel="kX">
        <!--texture>ui_btn_gray_long</texture-->
        <text align="c" font="graffiti22">ui_st_take_all</text>
		<text_color>
			<t r="231" g="168" b="12"/> <d r="181" g="170" b="148"/> <e r="238" g="153" b="26"/> <h r="255" g="255" b="255"/>
		</text_color>	
	</take_all_btn>
</window>

