	<string id="sedoy_jup_meet_0">
		<text>Встретиться с Седым</text>
	</string>
	<string id="sedoy_jup_meet_1">
		<text>Написать сообщение Седому с Юпитера</text>
	</string>
	<string id="sedoy_jup_meet_2">
		<text>Встретиться с Седым на Юпитере</text>
	</string>
	<string id="saharov_pda_0">
		<text>ПДА Призрака</text>
	</string>
	<string id="saharov_pda_1">
		<text>Найти ПДА Призрака</text>
	</string>
	<string id="saharov_pda_2">
		<text>Принести ПДА Сахарову</text>
	</string>
	<string id="borov_11_0">
		<text>Крушение вертолёта</text>
	</string>
	<string id="borov_11_1">
		<text>Найти вещи с вертолёта</text>
	</string>
	<string id="borov_11_2">
		<text>Отнести найденное Борову</text>
	</string>
	<string id="agroprom_vodka">
		<text>Водка для Шерстюка</text>
	</string>
	<string id="agroprom_vodka_0">
		<text>Собрать 20 бутылок водки</text>
	</string>
	<string id="agroprom_vodka_1">
		<text>Собрать водку</text>
	</string>
	<string id="agroprom_vodka_2">
		<text>Обменять водку на документы</text>
	</string>
	<string id="bandit_krisyk_0">
		<text>ПДА Крысюка</text>
	</string>
	<string id="bandit_krisyk_1">
		<text>Забрать ПДА с записями</text>
	</string>
	<string id="bandit_krisyk_2">
		<text>Отдать ПДА Борову</text>
	</string>
	<string id="about_life_heart_0">
		<text>Рецепт "Живого Сердца"</text>
	</string>
	<string id="about_life_heart_1">
		<text>Узнать компонент у Сахарова</text>
	</string>
	<string id="about_life_heart_2">
		<text>Узнать компонент у Бармена</text>
	</string>
	<string id="about_life_heart_3">
		<text>Узнать компонент у Сидоровича</text>
	</string>
	<string id="about_life_heart_4">
		<text>Поговорить с Доктором</text>
	</string>
	<string id="life_heart_sahar_0">
		<text>Установка прибора</text>
	</string>
	<string id="life_heart_sahar_1">
		<text>Установить прибор на ЧАЭС</text>
	</string>
	<string id="life_heart_sahar_2">
		<text>Поговорить с Сахаровым</text>
	</string>
	<string id="life_heart_sidor_0">
		<text>Контейнер с артефактом</text>
	</string>
	<string id="life_heart_sidor_1">
		<text>Найти контейнер в лесу на Радаре</text>
	</string>
	<string id="life_heart_sidor_2">
		<text>Доставить контейнер Сидоровичу</text>
	</string>
	<string id="life_heart_barman_0">
		<text>Флешка учёного</text>
	</string>
	<string id="life_heart_barman_1">
		<text>Найти флешку в Припяти</text>
	</string>
	<string id="life_heart_barman_2">
		<text>Доставить флешку Бармену</text>
	</string>
	<string id="life_heart_barman_hint">
		<text>Пропавший учёный</text>
	</string>
	<string id="strelok_pda_0">
		<text>ПДА Стрелка</text>
	</string>
	<string id="strelok_pda_1">
		<text>Найти ПДА Стрелка в Саркофаге</text>
	</string>
	<string id="strelok_pda_2">
		<text>Поговорить с Доктором</text>
	</string>
	<string id="strelok_pda2_0">
		<text>"Изумрудная медуза"</text>
	</string>
	<string id="strelok_pda2_1">
		<text>Найти "Изумрудную медузу"</text>
	</string>
	<string id="strelok_pda2_2">
		<text>Отдать артефакт Доктору</text>
	</string>
	<string id="strelok_pda2_hint">
		<text>Предполагаемое место</text>
	</string>